valuable/__about__.py
valuable/__init__.py
valuable/load.py
valuable/utils.py
valuable/xml.py
valuable-0.1.1.dist-info/DESCRIPTION.rst
valuable-0.1.1.dist-info/METADATA
valuable-0.1.1.dist-info/RECORD
valuable-0.1.1.dist-info/WHEEL
valuable-0.1.1.dist-info/metadata.json
valuable-0.1.1.dist-info/top_level.txt
