Metadata-Version: 2.0
Name: valuable
Version: 0.1.1
Summary: modular serialization tools
Home-page: https://github.com/ariebovenberg/valuable
Author: Arie Bovenberg
Author-email: a.c.bovenberg@gmail.com
License: MIT
Keywords: serialization,json,xml
Platform: UNKNOWN
Classifier: Development Status :: 3 - Alpha
Classifier: Intended Audience :: Developers
Classifier: License :: OSI Approved :: MIT License
Classifier: Programming Language :: Python :: 3
Classifier: Programming Language :: Python :: 3.5
Classifier: Programming Language :: Python :: 3.6
Classifier: Programming Language :: Python :: 3.7
Requires-Python: >=3.5
